repsys/__init__.py
repsys/__main__.py
repsys/cli.py
repsys/config.py
repsys/constants.py
repsys/core.py
repsys/dataset.py
repsys/dtypes.py
repsys/errors.py
repsys/evaluators.py
repsys/helpers.py
repsys/loaders.py
repsys/metrics.py
repsys/model.py
repsys/server.py
repsys/ui.py
repsys/validators.py
repsys/web/build/.DS_Store
repsys/web/build/android-chrome-192x192.png
repsys/web/build/android-chrome-512x512.png
repsys/web/build/apple-touch-icon.png
repsys/web/build/asset-manifest.json
repsys/web/build/favicon-16x16.png
repsys/web/build/favicon-32x32.png
repsys/web/build/favicon.ico
repsys/web/build/index.html
repsys/web/build/manifest.json
repsys/web/build/mockServiceWorker.js
repsys/web/build/robots.txt
repsys/web/build/static/css/main.be1e7917.css
repsys/web/build/static/css/main.be1e7917.css.map
repsys/web/build/static/js/main.a477bd6d.js
repsys/web/build/static/js/main.a477bd6d.js.LICENSE.txt
repsys/web/build/static/js/main.a477bd6d.js.map
repsys/web/build/static/media/roboto-latin-100-normal.25385d9f52e1ff5e8883.woff2
repsys/web/build/static/media/roboto-latin-100-normal.9391e6e27e41ec761fe1.woff
repsys/web/build/static/media/roboto-latin-300-normal.0109a2ace896a506a0aa.woff2
repsys/web/build/static/media/roboto-latin-300-normal.877b9231e5bb1f939daa.woff
repsys/web/build/static/media/roboto-latin-400-normal.4673b4537a84c7f7a130.woff2
repsys/web/build/static/media/roboto-latin-400-normal.9b78ea3bc4f00e508f01.woff
repsys/web/build/static/media/roboto-latin-500-normal.869888415d0b1a99ae5c.woff2
repsys/web/build/static/media/roboto-latin-500-normal.ddd11dabeca881d49f59.woff
repsys/web/build/static/media/roboto-latin-700-normal.0344cc3c5cd0959f5f92.woff
repsys/web/build/static/media/roboto-latin-700-normal.0682ca7f74351d42bf73.woff2
repsys/web/build/static/media/roboto-latin-900-normal.153ba331429b872012a6.woff2
repsys/web/build/static/media/roboto-latin-900-normal.b555d2282352d94691bc.woff
repsys_framework-0.4.1.dist-info/LICENSE.txt
repsys_framework-0.4.1.dist-info/METADATA
repsys_framework-0.4.1.dist-info/WHEEL
repsys_framework-0.4.1.dist-info/entry_points.txt
repsys_framework-0.4.1.dist-info/top_level.txt
repsys_framework-0.4.1.dist-info/RECORD
