Metadata-Version: 2.1
Name: repsys-framework
Version: 0.4.1
Summary: Framework for developing and analyzing recommender systems.
Home-page: https://github.com/cowjen01/repsys
Author: Jan Safarik
Author-email: safarj10@fit.cvut.cz
License: GPLv3
Requires-Python: >=3.8
License-File: LICENSE.txt
Requires-Dist: click (==8.1.6)
Requires-Dist: sanic (==22.6.2)
Requires-Dist: coloredlogs (==15.0.1)
Requires-Dist: numpy (==1.24.4)
Requires-Dist: scipy (==1.10.1)
Requires-Dist: pandas (==2.0.3)
Requires-Dist: bidict (==0.22.1)
Requires-Dist: scikit-learn (==1.3.0)
Requires-Dist: umap-learn (==0.5.3)
Requires-Dist: websockets (==10.4)
Provides-Extra: pymde
Requires-Dist: pymde (==0.1.18) ; extra == 'pymde'
Requires-Dist: pynndescent (==0.5.8) ; extra == 'pymde'
